odoo9_addon_l10n_nl_tax_statement-9.0.2.0.0-py3.8-nspkg.pth
odoo_addons/l10n_nl_tax_statement/README.rst
odoo_addons/l10n_nl_tax_statement/__init__.py
odoo_addons/l10n_nl_tax_statement/__openerp__.py
odoo_addons/l10n_nl_tax_statement/data/report_layouts.xml
odoo_addons/l10n_nl_tax_statement/i18n/l10n_nl_tax_statement.pot
odoo_addons/l10n_nl_tax_statement/i18n/nl.po
odoo_addons/l10n_nl_tax_statement/models/__init__.py
odoo_addons/l10n_nl_tax_statement/models/l10n_nl_vat_statement.py
odoo_addons/l10n_nl_tax_statement/models/l10n_nl_vat_statement_config.py
odoo_addons/l10n_nl_tax_statement/models/l10n_nl_vat_statement_line.py
odoo_addons/l10n_nl_tax_statement/report/report_tax_statement.xml
odoo_addons/l10n_nl_tax_statement/report/reports.xml
odoo_addons/l10n_nl_tax_statement/security/ir.model.access.csv
odoo_addons/l10n_nl_tax_statement/security/tax_statement_security_rule.xml
odoo_addons/l10n_nl_tax_statement/static/description/icon.png
odoo_addons/l10n_nl_tax_statement/static/src/css/report.css
odoo_addons/l10n_nl_tax_statement/tests/__init__.py
odoo_addons/l10n_nl_tax_statement/tests/test_l10n_nl_vat_statement.py
odoo_addons/l10n_nl_tax_statement/views/l10n_nl_vat_statement.xml
odoo_addons/l10n_nl_tax_statement/wizard/__init__.py
odoo_addons/l10n_nl_tax_statement/wizard/l10n_nl_vat_statement_config_wizard.py
odoo_addons/l10n_nl_tax_statement/wizard/l10n_nl_vat_statement_config_wizard.xml
odoo9_addon_l10n_nl_tax_statement-9.0.2.0.0.dist-info/METADATA
odoo9_addon_l10n_nl_tax_statement-9.0.2.0.0.dist-info/WHEEL
odoo9_addon_l10n_nl_tax_statement-9.0.2.0.0.dist-info/namespace_packages.txt
odoo9_addon_l10n_nl_tax_statement-9.0.2.0.0.dist-info/top_level.txt
odoo9_addon_l10n_nl_tax_statement-9.0.2.0.0.dist-info/RECORD
