Metadata-Version: 2.1
Name: odoo9-addon-l10n-nl-tax-statement
Version: 9.0.2.0.0
Summary: Netherlands BTW Statement
Home-page: https://github.com/OCA/l10n-netherlands
Author: Onestein, Odoo Community Association (OCA)
Author-email: support@odoo-community.org
License: AGPL-3
Platform: UNKNOWN
Classifier: Programming Language :: Python
Classifier: Framework :: Odoo
Classifier: Framework :: Odoo :: 9.0
Classifier: License :: OSI Approved :: GNU Affero General Public License v3
Requires-Python: ~=2.7
Requires-Dist: odoo9-addon-account-tax-balance
Requires-Dist: odoo <9.1a,>=9.0a
